{
  "hello": "أهلا بالعالم",
  "searchPlaceholder": "ما الذي تبحث عنه؟",
  "details": "تفاصيل",
  "by": "بواسطة",
  "HotOffers": "تريند العروض",
  "Categories": "الأقسام",
  "viewAll": "عرض الكل",
  "off": "خصم",
  "egp": "جنيه",
  "Nearest": "الأقرب",
  "New": "الأحدث",
  "SpecialOffers": "عروض خاصة",
  "Stores": "المتاجر",
  "Home": "الرئيسية",
  "Filter": "فلتر",
  "Location": "الموقع",
  "results": "نتائج",
  "Reset": "إعادة تعيين",
  "Category": "الفئة",
  "Type": "النوع",
  "Old": "الأقدم",
  "Select": "اختر",
  "Subscribe": "اشترك",
  "EnterYourEmail": "أدخل بريدك الإلكتروني",
  "SubscribeNow": "اشترك الآن",
  "CopyRight": " جميع الحقوق محفوظة Lift Media 2019 ©",
  "PrivacyPolicy": "سياسة الخصوصية",
  "TermsOfUse": "شروط الاستخدام",
  "Size": "الحجم",
  "Colors": "الألوان",
  "Red": "أحمر",
  "Blue": "أزرق",
  "Green": "أخضر",
  "Yellow": "أصفر",
  "Black": "أسود",
  "White": "أبيض",
  "Brown": "بني",
  "Mint": "نعناعي",
  "Orange": "برتقالي",
  "Price": "السعر",
  "Min": "الأدنى",
  "Max": "الأقصى",
  "LogIn": "تسجيل الدخول",
  "Register": "سجل الآن",
  "businessTypes": "أنواع الأعمال",
  "from": "من",
  "to": "إلى",
  "AboutUs": "من نحن",
  "Products": "المنتجات",
  "Offers": "العروض",
  "Reviews": "التقييمات",
  "AddYourReview": "أضف تقييمك",
  "SignUpFree": "سجل مجانا",
  "Hi": "مرحبا",
  "Submit": "تقديم",
  "AddAComment": "أضف تعليق",
  "GiveYourRating": "أعط تقييمك",
  "ShowMore": "أظهر المزيد",
  "SearchProducts" : "ابحث عن المنتجات",
  "Services": "الخدمات",
  "SaveStore": "إضافة الى المفضلة",
  "SuggestLogin": "تحتاج إلى تسجيل الدخول لاتمام هذا الإجراء",
  "Chats": "المحادثات",
  "TypeAMessage": "أكتب رسالة ...",
  "TypeToSearch": "أكتب لتبحث ...",
  "Online": "نشط"
}